calculo/__init__.py
calculo/preco_com_taxa.py
calculo-0.0.2.dist-info/METADATA
calculo-0.0.2.dist-info/WHEEL
calculo-0.0.2.dist-info/top_level.txt
calculo-0.0.2.dist-info/RECORD
