Metadata-Version: 2.1
Name: calculo
Version: 0.0.2
Summary: Cálculo
Home-page: https://github.com/joelsonalves/calculo.git
Author: Joelson Alves
Author-email: joelsonalves@yahoo.com.br
License: UNKNOWN
Platform: UNKNOWN
Requires-Python: >=3.0
